sudokum/__init__.py
sudokum/checker.py
sudokum/method/__init__.py
sudokum/method/mask.py
sudokum/method/types.py
sudokum/method/np_union/__init__.py
sudokum/method/np_union/generate.py
sudokum/method/np_union/solve.py
sudokum/method/wave_function_collapse/__init__.py
sudokum/method/wave_function_collapse/cell.py
sudokum/method/wave_function_collapse/generate.py
sudokum/method/wave_function_collapse/grid.py
sudokum/method/wave_function_collapse/pq.py
sudokum/method/wave_function_collapse/solve.py
sudokum/method/wave_function_collapse/view.py
sudokum-0.0.1.dist-info/LICENSE
sudokum-0.0.1.dist-info/METADATA
sudokum-0.0.1.dist-info/WHEEL
sudokum-0.0.1.dist-info/top_level.txt
sudokum-0.0.1.dist-info/RECORD
