Metadata-Version: 2.1
Name: sudokum
Version: 0.0.1
Summary: python sudoku generator and solver
Home-page: https://github.com/MorvanZhou/sudoku
Author: MorvanZhou
Author-email: morvanzhou@hotmail.com
Project-URL: Bug Tracker, https://github.com/MorvanZhou/sudoku/issues
Classifier: Programming Language :: Python :: 3
Classifier: License :: OSI Approved :: MIT License
Classifier: Operating System :: OS Independent
Requires-Python: >=3.6
License-File: LICENSE
Provides-Extra: build
Requires-Dist: tox (==3.24.3) ; extra == 'build'
Requires-Dist: build ; extra == 'build'
Requires-Dist: twine ; extra == 'build'
Requires-Dist: pylint ; extra == 'build'
Provides-Extra: numpy
Requires-Dist: numpy (>=1.19.5) ; extra == 'numpy'
